jsonmaster/__init__.py
jsonmaster/json_namespace.py
jsonmaster/types.py
jsonmaster/jsonfile/__init__.py
jsonmaster/jsonfile/json_file.py
jsonmaster/jsonfile/static_jsonfile.py
jsonmaster-1.0.1.dist-info/LICENSE
jsonmaster-1.0.1.dist-info/METADATA
jsonmaster-1.0.1.dist-info/WHEEL
jsonmaster-1.0.1.dist-info/top_level.txt
jsonmaster-1.0.1.dist-info/RECORD
