Metadata-Version: 2.1
Name: jsonmaster
Version: 1.0.1
Summary: A Python package for making your life of working with json's, easier
Home-page: https://github.com/EthanLerner1/jsonmaster
Author: Ethan Lerner
Author-email: lerner.ethan@gmail.com
License: UNKNOWN
Platform: UNKNOWN
Classifier: Development Status :: 3 - Alpha
Classifier: Intended Audience :: Developers
Classifier: License :: OSI Approved :: MIT License
Classifier: Programming Language :: Python :: 3
Classifier: Programming Language :: Python :: 3.6
Classifier: Programming Language :: Python :: 3.7
Classifier: Programming Language :: Python :: 3.8
Classifier: Programming Language :: Python :: 3.9
License-File: LICENSE
Requires-Dist: pydantic==2.9.2
Provides-Extra: dev
Requires-Dist: pytest; extra == "dev"
